validity/__init__.py
validity/validate.py
awsome_validity-0.0.1.dist-info/LICENSE
awsome_validity-0.0.1.dist-info/METADATA
awsome_validity-0.0.1.dist-info/WHEEL
awsome_validity-0.0.1.dist-info/top_level.txt
awsome_validity-0.0.1.dist-info/RECORD
