Metadata-Version: 2.1
Name: awsome-validity
Version: 0.0.1
Summary: awsome-validity is a package for Python that check if an email/phone/password... is valid
Author-email: rayzh <kribugzzz@outlook.com>
Project-URL: Homepage, https://github.com/Lorryrui/awsome-validity
Classifier: Programming Language :: Python :: 3
Classifier: License :: OSI Approved :: Apache Software License
Classifier: Operating System :: OS Independent
Requires-Python: >=3.8
License-File: LICENSE
